AuthEncoding/AuthEncoding.py
AuthEncoding/__init__.py
AuthEncoding/compat.py
AuthEncoding/tests/__init__.py
AuthEncoding/tests/test_AuthEncoding.py
AuthEncoding-5.0.dist-info/LICENSE.txt
AuthEncoding-5.0.dist-info/METADATA
AuthEncoding-5.0.dist-info/WHEEL
AuthEncoding-5.0.dist-info/top_level.txt
AuthEncoding-5.0.dist-info/RECORD
