Metadata-Version: 2.1
Name: AuthEncoding
Version: 5.0
Summary: Framework for handling LDAP style password hashes.
Home-page: https://github.com/zopefoundation/AuthEncoding
Author: Zope Foundation and Contributors
Author-email: zope-dev@zope.org
License: ZPL 2.1
Project-URL: Sources, https://github.com/zopefoundation/AuthEncoding
Project-URL: Issue Tracker, https://github.com/zopefoundation/AuthEncoding/issues
Classifier: Development Status :: 6 - Mature
Classifier: Environment :: Web Environment
Classifier: Framework :: Zope2
Classifier: Framework :: Zope
Classifier: Framework :: Zope :: 2
Classifier: Framework :: Zope :: 4
Classifier: Framework :: Zope :: 5
Classifier: License :: OSI Approved :: Zope Public License
Classifier: Operating System :: OS Independent
Classifier: Programming Language :: Python
Classifier: Programming Language :: Python :: 3
Classifier: Programming Language :: Python :: 3.7
Classifier: Programming Language :: Python :: 3.8
Classifier: Programming Language :: Python :: 3.9
Classifier: Programming Language :: Python :: 3.10
Classifier: Programming Language :: Python :: 3.11
Classifier: Programming Language :: Python :: Implementation :: CPython
Classifier: Programming Language :: Python :: Implementation :: PyPy
Classifier: Topic :: System :: Systems Administration :: Authentication/Directory :: LDAP
Requires-Python: >=3.7
Provides-Extra: test
Provides-Extra: bcrypt
License-File: LICENSE.txt
